odoo/addons/hr_expense_advance_clearing_sequence/README.rst
odoo/addons/hr_expense_advance_clearing_sequence/__init__.py
odoo/addons/hr_expense_advance_clearing_sequence/__manifest__.py
odoo/addons/hr_expense_advance_clearing_sequence/data/hr_expense_data.xml
odoo/addons/hr_expense_advance_clearing_sequence/i18n/hr_expense_advance_clearing_sequence.pot
odoo/addons/hr_expense_advance_clearing_sequence/i18n/it.po
odoo/addons/hr_expense_advance_clearing_sequence/i18n/pt_BR.po
odoo/addons/hr_expense_advance_clearing_sequence/models/__init__.py
odoo/addons/hr_expense_advance_clearing_sequence/models/hr_expense_sheet.py
odoo/addons/hr_expense_advance_clearing_sequence/readme/CONFIGURE.rst
odoo/addons/hr_expense_advance_clearing_sequence/readme/CONTRIBUTORS.rst
odoo/addons/hr_expense_advance_clearing_sequence/readme/DESCRIPTION.rst
odoo/addons/hr_expense_advance_clearing_sequence/static/description/icon.png
odoo/addons/hr_expense_advance_clearing_sequence/static/description/index.html
odoo/addons/hr_expense_advance_clearing_sequence/tests/__init__.py
odoo/addons/hr_expense_advance_clearing_sequence/tests/test_hr_expense_advance_clearing_sequence.py
odoo12_addon_hr_expense_advance_clearing_sequence-12.0.1.0.0.99.dev10.dist-info/METADATA
odoo12_addon_hr_expense_advance_clearing_sequence-12.0.1.0.0.99.dev10.dist-info/WHEEL
odoo12_addon_hr_expense_advance_clearing_sequence-12.0.1.0.0.99.dev10.dist-info/top_level.txt
odoo12_addon_hr_expense_advance_clearing_sequence-12.0.1.0.0.99.dev10.dist-info/RECORD
